{
  "annotations": {
    "list": [
      {
        "builtIn": 1,
        "datasource": {
          "type": "grafana",
          "uid": "-- Grafana --"
        },
        "enable": true,
        "hide": true,
        "iconColor": "rgba(0, 211, 255, 1)",
        "name": "Annotations & Alerts",
        "type": "dashboard"
      }
    ]
  },
  "editable": true,
  "fiscalYearStartMonth": 0,
  "graphTooltip": 0,
  "links": [],
  "panels": [
    {
      "collapsed": false,
      "gridPos": {
        "h": 1,
        "w": 24,
        "x": 0,
        "y": 0
      },
      "id": 4,
      "panels": [],
      "title": "Errors",
      "type": "row"
    },
    {
      "datasource": {
        "type": "loki",
        "uid": "P8E80F9AEF21F6940"
      },
      "fieldConfig": {
        "defaults": {
          "color": {
            "mode": "palette-classic"
          },
          "custom": {
            "axisBorderShow": false,
            "axisCenteredZero": false,
            "axisColorMode": "text",
            "axisLabel": "",
            "axisPlacement": "auto",
            "barAlignment": 0,
            "drawStyle": "line",
            "fillOpacity": 0,
            "gradientMode": "none",
            "hideFrom": {
              "legend": false,
              "tooltip": false,
              "viz": false
            },
            "insertNulls": false,
            "lineInterpolation": "stepAfter",
            "lineWidth": 2,
            "pointSize": 5,
            "scaleDistribution": {
              "log": 2,
              "type": "symlog"
            },
            "showPoints": "auto",
            "spanNulls": true,
            "stacking": {
              "group": "A",
              "mode": "none"
            },
            "thresholdsStyle": {
              "mode": "off"
            }
          },
          "mappings": [],
          "thresholds": {
            "mode": "absolute",
            "steps": [
              {
                "color": "green",
                "value": null
              },
              {
                "color": "red",
                "value": 80
              }
            ]
          }
        },
        "overrides": [
          {
            "matcher": {
              "id": "byName",
              "options": "{detected_level=\"error\"}"
            },
            "properties": [
              {
                "id": "color",
                "value": {
                  "fixedColor": "#F2495C",
                  "mode": "fixed"
                }
              }
            ]
          },
          {
            "matcher": {
              "id": "byName",
              "options": "{}"
            },
            "properties": [
              {
                "id": "color",
                "value": {
                  "fixedColor": "super-light-blue",
                  "mode": "fixed"
                }
              }
            ]
          },
          {
            "matcher": {
              "id": "byName",
              "options": "{detected_level=\"warn\"}"
            },
            "properties": [
              {
                "id": "color",
                "value": {
                  "fixedColor": "yellow",
                  "mode": "fixed"
                }
              }
            ]
          },
          {
            "matcher": {
              "id": "byName",
              "options": "{detected_level=\"info\"}"
            },
            "properties": [
              {
                "id": "color",
                "value": {
                  "fixedColor": "green",
                  "mode": "fixed"
                }
              }
            ]
          },
          {
            "matcher": {
              "id": "byName",
              "options": "{detected_level=\"debug\"}"
            },
            "properties": [
              {
                "id": "color",
                "value": {
                  "fixedColor": "orange",
                  "mode": "fixed"
                }
              }
            ]
          }
        ]
      },
      "gridPos": {
        "h": 10,
        "w": 24,
        "x": 0,
        "y": 1
      },
      "id": 2,
      "options": {
        "legend": {
          "calcs": [
            "count"
          ],
          "displayMode": "table",
          "placement": "right",
          "showLegend": true,
          "sortBy": "Count",
          "sortDesc": true
        },
        "tooltip": {
          "mode": "single",
          "sort": "none"
        }
      },
      "targets": [
        {
          "datasource": {
            "type": "loki",
            "uid": "P8E80F9AEF21F6940"
          },
          "editorMode": "builder",
          "expr": "sum by(host, unit) (rate({job=\"systemd-journal\", host=\"$test\"} | logfmt | detected_level = `error` [$__auto]))",
          "queryType": "range",
          "refId": "A"
        }
      ],
      "title": "by host and unit",
      "type": "timeseries"
    },
    {
      "datasource": {
        "type": "loki",
        "uid": "P8E80F9AEF21F6940"
      },
      "gridPos": {
        "h": 10,
        "w": 24,
        "x": 0,
        "y": 11
      },
      "id": 7,
      "options": {
        "dedupStrategy": "numbers",
        "enableLogDetails": true,
        "prettifyLogMessage": true,
        "showCommonLabels": true,
        "showLabels": false,
        "showTime": true,
        "sortOrder": "Descending",
        "wrapLogMessage": true
      },
      "targets": [
        {
          "datasource": {
            "type": "loki",
            "uid": "P8E80F9AEF21F6940"
          },
          "editorMode": "builder",
          "expr": "{job=\"systemd-journal\", host=\"$test\"} | logfmt | detected_level = `error`",
          "queryType": "range",
          "refId": "A"
        }
      ],
      "type": "logs"
    },
    {
      "collapsed": false,
      "gridPos": {
        "h": 1,
        "w": 24,
        "x": 0,
        "y": 21
      },
      "id": 5,
      "panels": [],
      "title": "Warning",
      "type": "row"
    },
    {
      "datasource": {
        "type": "loki",
        "uid": "P8E80F9AEF21F6940"
      },
      "fieldConfig": {
        "defaults": {
          "color": {
            "mode": "palette-classic"
          },
          "custom": {
            "axisBorderShow": false,
            "axisCenteredZero": false,
            "axisColorMode": "text",
            "axisLabel": "",
            "axisPlacement": "auto",
            "barAlignment": 0,
            "drawStyle": "line",
            "fillOpacity": 0,
            "gradientMode": "none",
            "hideFrom": {
              "legend": false,
              "tooltip": false,
              "viz": false
            },
            "insertNulls": false,
            "lineInterpolation": "stepAfter",
            "lineWidth": 2,
            "pointSize": 5,
            "scaleDistribution": {
              "log": 2,
              "type": "symlog"
            },
            "showPoints": "auto",
            "spanNulls": true,
            "stacking": {
              "group": "A",
              "mode": "none"
            },
            "thresholdsStyle": {
              "mode": "off"
            }
          },
          "mappings": [],
          "thresholds": {
            "mode": "absolute",
            "steps": [
              {
                "color": "green",
                "value": null
              },
              {
                "color": "red",
                "value": 80
              }
            ]
          }
        },
        "overrides": [
          {
            "matcher": {
              "id": "byName",
              "options": "{detected_level=\"error\"}"
            },
            "properties": [
              {
                "id": "color",
                "value": {
                  "fixedColor": "#F2495C",
                  "mode": "fixed"
                }
              }
            ]
          },
          {
            "matcher": {
              "id": "byName",
              "options": "{}"
            },
            "properties": [
              {
                "id": "color",
                "value": {
                  "fixedColor": "super-light-blue",
                  "mode": "fixed"
                }
              }
            ]
          },
          {
            "matcher": {
              "id": "byName",
              "options": "{detected_level=\"warn\"}"
            },
            "properties": [
              {
                "id": "color",
                "value": {
                  "fixedColor": "yellow",
                  "mode": "fixed"
                }
              }
            ]
          },
          {
            "matcher": {
              "id": "byName",
              "options": "{detected_level=\"info\"}"
            },
            "properties": [
              {
                "id": "color",
                "value": {
                  "fixedColor": "green",
                  "mode": "fixed"
                }
              }
            ]
          },
          {
            "matcher": {
              "id": "byName",
              "options": "{detected_level=\"debug\"}"
            },
            "properties": [
              {
                "id": "color",
                "value": {
                  "fixedColor": "orange",
                  "mode": "fixed"
                }
              }
            ]
          }
        ]
      },
      "gridPos": {
        "h": 10,
        "w": 24,
        "x": 0,
        "y": 22
      },
      "id": 6,
      "options": {
        "legend": {
          "calcs": [
            "count"
          ],
          "displayMode": "table",
          "placement": "right",
          "showLegend": true,
          "sortBy": "Count",
          "sortDesc": true
        },
        "tooltip": {
          "mode": "single",
          "sort": "none"
        }
      },
      "targets": [
        {
          "datasource": {
            "type": "loki",
            "uid": "P8E80F9AEF21F6940"
          },
          "editorMode": "builder",
          "expr": "sum by(host, unit) (rate({job=\"systemd-journal\"} | logfmt | detected_level = `warn` [$__auto]))",
          "queryType": "range",
          "refId": "A"
        }
      ],
      "title": "by host and unit",
      "type": "timeseries"
    },
    {
      "datasource": {
        "type": "loki",
        "uid": "P8E80F9AEF21F6940"
      },
      "gridPos": {
        "h": 10,
        "w": 24,
        "x": 0,
        "y": 32
      },
      "id": 3,
      "options": {
        "dedupStrategy": "numbers",
        "enableLogDetails": true,
        "prettifyLogMessage": true,
        "showCommonLabels": true,
        "showLabels": true,
        "showTime": true,
        "sortOrder": "Descending",
        "wrapLogMessage": true
      },
      "targets": [
        {
          "datasource": {
            "type": "loki",
            "uid": "P8E80F9AEF21F6940"
          },
          "editorMode": "builder",
          "expr": "{job=\"systemd-journal\"} | logfmt | detected_level = `warn`",
          "queryType": "range",
          "refId": "A"
        }
      ],
      "type": "logs"
    }
  ],
  "refresh": "",
  "schemaVersion": 39,
  "tags": [
    "loki"
  ],
  "templating": {
    "list": [
      {
        "current": {
          "selected": true,
          "text": "oide",
          "value": "oide"
        },
        "datasource": {
          "type": "loki",
          "uid": "P8E80F9AEF21F6940"
        },
        "definition": "",
        "hide": 0,
        "includeAll": false,
        "multi": false,
        "name": "test",
        "options": [],
        "query": {
          "label": "host",
          "refId": "LokiVariableQueryEditor-VariableQuery",
          "stream": "",
          "type": 1
        },
        "refresh": 1,
        "regex": "",
        "skipUrlSync": false,
        "sort": 0,
        "type": "query"
      }
    ]
  },
  "time": {
    "from": "now-7d",
    "to": "now"
  },
  "timepicker": {},
  "timezone": "browser",
  "title": "Logs",
  "uid": "fdvts2k4sxgxsc",
  "version": 1,
  "weekStart": ""
}